loggerpython/__init__.py
loggerpython/logger.py
loggerpython-0.1.0.dist-info/licenses/LICENSE
loggerpython-0.1.0.dist-info/METADATA
loggerpython-0.1.0.dist-info/WHEEL
loggerpython-0.1.0.dist-info/top_level.txt
loggerpython-0.1.0.dist-info/RECORD
