Metadata-Version: 2.4
Name: loggerpython
Version: 0.1.0
Summary: A Simple Python Logging Framework.
Home-page: https://github.com/mainframematrix/LoggerPython
Author: Mainframe Matrix
Author-email: mainframematrix01@gmail.com
Classifier: Programming Language :: Python :: 3
Classifier: License :: OSI Approved :: MIT License
Classifier: Operating System :: OS Independent
Requires-Python: >=3.7
License-File: LICENSE
Dynamic: author
Dynamic: author-email
Dynamic: classifier
Dynamic: description
Dynamic: description-content-type
Dynamic: home-page
Dynamic: license-file
Dynamic: requires-python
Dynamic: summary
